backtradingbot/__init__.py
backtradingbot/core.py
backtradingbot-0.1.5.dist-info/METADATA
backtradingbot-0.1.5.dist-info/WHEEL
backtradingbot-0.1.5.dist-info/entry_points.txt
backtradingbot-0.1.5.dist-info/top_level.txt
backtradingbot-0.1.5.dist-info/RECORD
