Metadata-Version: 2.4
Name: backtradingbot
Version: 0.1.5
Summary: This is a back trading bot using python
Author-email: Your Name <benbates2025@gmail.com>
License: MIT
Requires-Python: >=3.8
